djangochurch_docs_theme
