Metadata-Version: 1.1
Name: djangochurch-docs-theme
Version: 0.1.1
Summary: Django Church Sphinx theme.
Home-page: https://github.com/djangochurch/djangochurch_docs_theme/
Author: Django Church
Author-email: info@djangochurch.org
License: MIT
Platform: UNKNOWN
Classifier: Development Status :: 3 - Alpha
Classifier: License :: OSI Approved :: BSD License
Classifier: Environment :: Console
Classifier: Environment :: Web Environment
Classifier: Intended Audience :: Developers
Classifier: Programming Language :: Python :: 2.7
Classifier: Programming Language :: Python :: 3
Classifier: Operating System :: OS Independent
Classifier: Topic :: Documentation
Classifier: Topic :: Software Development :: Documentation
